CHANGELOG.md
LICENSE
MANIFEST.in
README.md
pyproject.toml
requirements.txt
setup.cfg
setup.py
pyadminkit/__init__.py
pyadminkit/cli.py
pyadminkit.egg-info/PKG-INFO
pyadminkit.egg-info/SOURCES.txt
pyadminkit.egg-info/dependency_links.txt
pyadminkit.egg-info/entry_points.txt
pyadminkit.egg-info/not-zip-safe
pyadminkit.egg-info/requires.txt
pyadminkit.egg-info/top_level.txt
pyadminkit/core/__init__.py
pyadminkit/core/database/__init__.py
pyadminkit/core/database/connection.py
pyadminkit/core/database/manager.py
pyadminkit/core/database/migrations.py
pyadminkit/core/database/models.py
pyadminkit/core/database/query.py