Metadata-Version: 2.4
Name: pyadminkit
Version: 0.1.3
Summary: A lightweight and highly extensible Python admin system middleware
Home-page: https://github.com/pyadminkit/pyadminkit
Author: PyAdminKit Team
Author-email: PyAdminKit Team <admin@pyadminkit.com>
Maintainer-email: PyAdminKit Team <admin@pyadminkit.com>
License: MIT
Project-URL: Homepage, https://github.com/pyadminkit/pyadminkit
Project-URL: Documentation, https://pyadminkit.readthedocs.io/
Project-URL: Repository, https://github.com/pyadminkit/pyadminkit.git
Project-URL: Bug Reports, https://github.com/pyadminkit/pyadminkit/issues
Project-URL: Changelog, https://github.com/pyadminkit/pyadminkit/blob/main/CHANGELOG.md
Keywords: admin,dashboard,cms,management,database,orm,fastapi,flask,django,async,mysql,postgresql,sqlite,mongodb,crud,api,web,framework
Classifier: Development Status :: 3 - Alpha
Classifier: Intended Audience :: Developers
Classifier: Topic :: Software Development :: Libraries :: Python Modules
Classifier: Topic :: Database
Classifier: Topic :: Internet :: WWW/HTTP :: Dynamic Content
Classifier: Topic :: Office/Business
Classifier: License :: OSI Approved :: MIT License
Classifier: Programming Language :: Python :: 3
Classifier: Programming Language :: Python :: 3.8
Classifier: Programming Language :: Python :: 3.9
Classifier: Programming Language :: Python :: 3.10
Classifier: Programming Language :: Python :: 3.11
Classifier: Programming Language :: Python :: 3.12
Classifier: Operating System :: OS Independent
Classifier: Framework :: AsyncIO
Classifier: Framework :: FastAPI
Classifier: Framework :: Flask
Classifier: Framework :: Django
Requires-Python: >=3.8
License-File: LICENSE
Requires-Dist: pydantic>=2.0.0
Requires-Dist: typing-extensions>=4.0.0
Provides-Extra: mysql
Requires-Dist: aiomysql>=0.2.0; extra == "mysql"
Provides-Extra: postgresql
Requires-Dist: asyncpg>=0.28.0; extra == "postgresql"
Provides-Extra: sqlite
Requires-Dist: aiosqlite>=0.19.0; extra == "sqlite"
Provides-Extra: mongodb
Requires-Dist: motor>=3.3.0; extra == "mongodb"
Provides-Extra: fastapi
Requires-Dist: fastapi>=0.100.0; extra == "fastapi"
Provides-Extra: flask
Requires-Dist: flask>=2.0.0; extra == "flask"
Provides-Extra: django
Requires-Dist: django>=4.0.0; extra == "django"
Provides-Extra: full
Requires-Dist: aiomysql>=0.2.0; extra == "full"
Requires-Dist: asyncpg>=0.28.0; extra == "full"
Requires-Dist: aiosqlite>=0.19.0; extra == "full"
Requires-Dist: motor>=3.3.0; extra == "full"
Requires-Dist: fastapi>=0.100.0; extra == "full"
Requires-Dist: flask>=2.0.0; extra == "full"
Provides-Extra: dev
Requires-Dist: pytest>=7.0.0; extra == "dev"
Requires-Dist: pytest-asyncio>=0.21.0; extra == "dev"
Requires-Dist: black>=23.0.0; extra == "dev"
Requires-Dist: isort>=5.12.0; extra == "dev"
Requires-Dist: flake8>=6.0.0; extra == "dev"
Requires-Dist: mypy>=1.5.0; extra == "dev"
Requires-Dist: pre-commit>=3.0.0; extra == "dev"
Requires-Dist: twine>=4.0.0; extra == "dev"
Requires-Dist: build>=0.10.0; extra == "dev"
Dynamic: author
Dynamic: home-page
Dynamic: license-file
Dynamic: requires-python
